mkdocs_mknodes/__init__.py
mkdocs_mknodes/appconfig/__init__.py
mkdocs_mknodes/appconfig/appconfig.py
mkdocs_mknodes/appconfig/base.py
mkdocs_mknodes/appconfig/jinjaconfig.py
mkdocs_mknodes/appconfig/themeconfig.py
mkdocs_mknodes/appconfig/upathtype.py
mkdocs_mknodes/appconfig/validationconfig.py
mkdocs_mknodes/backends/__init__.py
mkdocs_mknodes/backends/buildbackend.py
mkdocs_mknodes/backends/markdownbackend.py
mkdocs_mknodes/backends/mkdocsbackend.py
mkdocs_mknodes/buildcollector.py
mkdocs_mknodes/buildcontext.py
mkdocs_mknodes/builders/__init__.py
mkdocs_mknodes/builders/configbuilder.py
mkdocs_mknodes/cli/__init__.py
mkdocs_mknodes/cli/richstate.py
mkdocs_mknodes/commands/__init__.py
mkdocs_mknodes/commands/build_page.py
mkdocs_mknodes/commands/serve.py
mkdocs_mknodes/commands/utils.py
mkdocs_mknodes/liveserver.py
mkdocs_mknodes/manual/__init__.py
mkdocs_mknodes/manual/cli_section.py
mkdocs_mknodes/manual/get_started_section.py
mkdocs_mknodes/manual/github_index.py
mkdocs_mknodes/manual/root.py
mkdocs_mknodes/manual/use_cases_section.py
mkdocs_mknodes/mkdefaultwebsite.py
mkdocs_mknodes/mkdocsconfig.py
mkdocs_mknodes/paths.py
mkdocs_mknodes/plugin/__init__.py
mkdocs_mknodes/plugin/mkdocsbuilder.py
mkdocs_mknodes/plugin/mkdocshelpers.py
mkdocs_mknodes/plugin/mknodesconfig.py
mkdocs_mknodes/plugin/pluginconfig.py
mkdocs_mknodes/plugin/rewriteloader.py
mkdocs_mknodes/py.typed
mkdocs_mknodes/resources/mkdocs_basic.yml
mkdocs_mknodes/resources/timeline_data.toml
mkdocs_mknodes/telemetry.py
mkdocs_mknodes-1.1.0.dist-info/licenses/LICENSE
mkdocs_mknodes-1.1.0.dist-info/WHEEL
mkdocs_mknodes-1.1.0.dist-info/entry_points.txt
mkdocs_mknodes-1.1.0.dist-info/METADATA
mkdocs_mknodes-1.1.0.dist-info/RECORD
