Metadata-Version: 2.4
Name: mkdocs-mknodes
Version: 1.1.0
Summary: Don't write docs. Code them.
Keywords: docs,docstrings,documentation,framework,internet,markdown
Author: Philipp Temminghoff
Author-email: Philipp Temminghoff <philipptemminghoff@gmail.com>
License-Expression: MIT
License-File: LICENSE
Classifier: Development Status :: 4 - Beta
Classifier: Intended Audience :: Developers
Classifier: Operating System :: OS Independent
Classifier: Programming Language :: Python :: 3
Classifier: Programming Language :: Python :: 3 :: Only
Classifier: Programming Language :: Python :: 3.13
Classifier: Programming Language :: Python :: 3.14
Classifier: Programming Language :: Python :: Implementation :: CPython
Classifier: Topic :: Documentation
Classifier: Topic :: Internet
Classifier: Topic :: Software Development :: Documentation
Classifier: Topic :: Software Development :: User Interfaces
Classifier: Topic :: Text Processing :: Markup :: Markdown
Requires-Dist: anyenv>=0.1.0
Requires-Dist: jinja2
Requires-Dist: jinjarope
Requires-Dist: logfire>4.0
Requires-Dist: mkdocs>=1.5
Requires-Dist: mknodes>=2.1.0a1
Requires-Dist: pathspec
Requires-Dist: pydantic
Requires-Dist: rich
Requires-Dist: typer
Requires-Dist: universal-pathlib
Requires-Dist: upathtools>=0.6.5
Requires-Dist: yamling
Requires-Dist: yarl>=1.17.1
Requires-Python: >=3.13
Project-URL: Documentation, https://phil65.github.io/mkdocs-mknodes/
Project-URL: Gitter, https://app.gitter.im/#/room/#mknodes:gitter.im
Project-URL: Source, https://github.com/phil65/mkdocs_mknodes
